netcdf_segy/__init__.py
netcdf_segy/segy2netcdf.py
netcdf_segy-1.0.1.dist-info/LICENSE
netcdf_segy-1.0.1.dist-info/METADATA
netcdf_segy-1.0.1.dist-info/WHEEL
netcdf_segy-1.0.1.dist-info/entry_points.txt
netcdf_segy-1.0.1.dist-info/top_level.txt
netcdf_segy-1.0.1.dist-info/RECORD
