Metadata-Version: 2.1
Name: netcdf-segy
Version: 1.0.1
Summary: Convert between SEG-Y and NetCDF
Home-page: https://github.com/ar4/netcdf_segy
Author: Alan Richardson
Author-email: arichar@tcd.ie
License: GNU General Public License v3
Keywords: netcdf_segy
Platform: UNKNOWN
Classifier: Development Status :: 2 - Pre-Alpha
Classifier: Intended Audience :: Developers
Classifier: License :: OSI Approved :: GNU General Public License v3 (GPLv3)
Classifier: Natural Language :: English
Classifier: Programming Language :: Python :: 2
Classifier: Programming Language :: Python :: 2.7
Classifier: Programming Language :: Python :: 3
Classifier: Programming Language :: Python :: 3.4
Classifier: Programming Language :: Python :: 3.5
Requires-Dist: Click (>=6.0)
Requires-Dist: segyio
Requires-Dist: netCDF4
Requires-Dist: numpy
